<?xml version="1.0" encoding="UTF-8"?>
<!DOCTYPE tiles-definitions PUBLIC "-//Apache Software Foundation//DTD Tiles Configuration 3.0//EN" 
"http://tiles.apache.org/dtds/tiles-config_3_0.dtd">
<tiles-definitions>
	<definition name=".main" template="/WEB-INF/views/main/layout.jsp">
	 	<put-attribute name="header" value="/WEB-INF/views/main/header.jsp"/>
	 	<put-attribute name="body" value="/WEB-INF/views/main/home.jsp"/>
	 	<put-attribute name="footer" value="/WEB-INF/views/main/footer.jsp"/>
	</definition>
	
	
	<definition name=".admin.main" extends=".main">
		<put-attribute name="body" value="/WEB-INF/views/admin/main.jsp"/>
	</definition>
	<!-- 로그인 메인페이지로 이동  -->
	<definition name=".login.main" extends=".main">
		<put-attribute name="body" value="/WEB-INF/views/login/main.jsp"/>
	</definition>
	<!--  상세 검색 페이지로 이동 -->
	<definition name=".search.main" extends=".main">
		<put-attribute name="body" value="/WEB-INF/views/search/search.jsp"/>
	</definition>
</tiles-definitions>































